Metadata-Version: 1.0
Name: propriecle
Version: 0.1.1
Summary: something something vault master keys
Home-page: https://github.com/autodesk/propriecle
Author: Jonathan Freedman
Author-email: jonathan.freedman@autodesk.com
License: MIT
Platform: UNKNOWN
